{"id":"3wT5Z8wB6R9tJpIcwHIcW","title":"Chapter 071 - Making Friends","desc":"","updated":1643626558015,"created":1643569467618,"custom":{},"fname":"volume-1.chapter-071","type":"note","vault":{"fsPath":"vault"},"contentHash":"fff8375fe430c06cc199130148c4b346","links":[{"type":"wiki","from":{"fname":"volume-1.chapter-071","id":"3wT5Z8wB6R9tJpIcwHIcW","vaultName":"vault"},"value":"volume-1.chapter-072","position":{"start":{"line":103,"column":3,"offset":10290},"end":{"line":103,"column":27,"offset":10314},"indent":[]},"xvault":false,"sameFile":false,"to":{"fname":"volume-1.chapter-072"}},{"from":{"fname":"volume-1.chapter-070","id":"0bCqwx1PvbUniNK0li0Nz","vaultName":"vault"},"type":"backlink","position":{"start":{"line":93,"column":3,"offset":9781},"end":{"line":93,"column":27,"offset":9805},"indent":[]},"value":"volume-1.chapter-071"}],"anchors":{},"children":[],"parent":"YmDf44XQK0snHWr4HCNuj","data":{}}
