{"id":"kwlh33nqwfe4l2rtkh6oquy","title":"Chapter 179 - Insurmountable Wall","desc":"","updated":1653628279634,"created":1651742486106,"custom":{},"fname":"volume-3.chapter-179","type":"note","vault":{"fsPath":"vault"},"contentHash":"51990b0c6e2de5fc7f4168e6e86bfff4","links":[{"type":"wiki","from":{"fname":"volume-3.chapter-179","id":"kwlh33nqwfe4l2rtkh6oquy","vaultName":"vault"},"value":"volume-3.chapter-180","position":{"start":{"line":105,"column":3,"offset":11326},"end":{"line":105,"column":27,"offset":11350},"indent":[]},"xvault":false,"sameFile":false,"to":{"fname":"volume-3.chapter-180"}},{"from":{"fname":"volume-3.chapter-178","id":"zj9wbj421c6s4qwfhpcys0l","vaultName":"vault"},"type":"backlink","position":{"start":{"line":85,"column":3,"offset":11541},"end":{"line":85,"column":27,"offset":11565},"indent":[]},"value":"volume-3.chapter-179"}],"anchors":{},"children":[],"parent":"hk3a0wjaksh6uap9l9fm0wn","data":{}}
