{"id":"nB7lGOAd7kCMof7T8oRDG","title":"Chapter 124 - Do Not Try This At Home (Redux)","desc":"","updated":1643657657716,"created":1643655636040,"custom":{},"fname":"volume-2.chapter-124","type":"note","vault":{"fsPath":"vault"},"contentHash":"ac8169b3c6b5dfaee535edb9f1ba4ae6","links":[{"type":"wiki","from":{"fname":"volume-2.chapter-124","id":"nB7lGOAd7kCMof7T8oRDG","vaultName":"vault"},"value":"volume-2.chapter-125","position":{"start":{"line":135,"column":3,"offset":12466},"end":{"line":135,"column":27,"offset":12490},"indent":[]},"xvault":false,"sameFile":false,"to":{"fname":"volume-2.chapter-125"}},{"from":{"fname":"volume-2.chapter-123","id":"vlfbRPCPYMVdb9Z5S8wkH","vaultName":"vault"},"type":"backlink","position":{"start":{"line":97,"column":3,"offset":10341},"end":{"line":97,"column":27,"offset":10365},"indent":[]},"value":"volume-2.chapter-124"}],"anchors":{},"children":[],"parent":"9BHUWZMl1JRvE5LoAphKR","data":{}}
