{"id":"oz30yelr9xu606du8j3e11g","title":"Chapter 295 - A Physician's Oath","desc":"","updated":1679290158640,"created":1677153076621,"custom":{},"fname":"volume-4.chapter-295","type":"note","vault":{"fsPath":"vault"},"contentHash":"c0848779cae51574b26b4fc4db14e752","links":[{"type":"wiki","from":{"fname":"volume-4.chapter-295","id":"oz30yelr9xu606du8j3e11g","vaultName":"vault"},"value":"volume-4.chapter-296","position":{"start":{"line":81,"column":3,"offset":9818},"end":{"line":81,"column":27,"offset":9842},"indent":[]},"xvault":false,"sameFile":false,"to":{"fname":"volume-4.chapter-296"}},{"from":{"fname":"volume-4.chapter-294","id":"h3wyum8dq8kcjyesbvcqxbh","vaultName":"vault"},"type":"backlink","position":{"start":{"line":129,"column":3,"offset":10833},"end":{"line":129,"column":27,"offset":10857},"indent":[]},"value":"volume-4.chapter-295"}],"anchors":{},"children":[],"parent":"enpadrm33suumrdjl5t6gt2","data":{}}
