{"id":"qf4b3vv3tpbnr2pgg0s8pr8","title":"Chapter 256 - Burdened by Expectations","desc":"","updated":1670403749829,"created":1668358019303,"custom":{},"fname":"volume-4.chapter-256","type":"note","vault":{"fsPath":"vault"},"contentHash":"7a3e361d50cf153ce98200cafb3679d4","links":[{"type":"wiki","from":{"fname":"volume-4.chapter-256","id":"qf4b3vv3tpbnr2pgg0s8pr8","vaultName":"vault"},"value":"volume-4.chapter-257","position":{"start":{"line":77,"column":3,"offset":9704},"end":{"line":77,"column":27,"offset":9728},"indent":[]},"xvault":false,"sameFile":false,"to":{"fname":"volume-4.chapter-257"}},{"from":{"fname":"volume-4.chapter-255","id":"ihfywo0owkgmrugy5evchnj","vaultName":"vault"},"type":"backlink","position":{"start":{"line":83,"column":3,"offset":10360},"end":{"line":83,"column":27,"offset":10384},"indent":[]},"value":"volume-4.chapter-256"}],"anchors":{},"children":[],"parent":"enpadrm33suumrdjl5t6gt2","data":{}}
