{"id":"x3pPQ5S9Xwoxwc6FoaXRj","title":"Chapter 052 - Swish and Flick!","desc":"","updated":1643623045504,"created":1643569397622,"custom":{},"fname":"volume-1.chapter-052","type":"note","vault":{"fsPath":"vault"},"contentHash":"0df2c7e9c16831d3c811adaa41758cfe","links":[{"type":"wiki","from":{"fname":"volume-1.chapter-052","id":"x3pPQ5S9Xwoxwc6FoaXRj","vaultName":"vault"},"value":"volume-1.chapter-053","position":{"start":{"line":73,"column":3,"offset":9291},"end":{"line":73,"column":27,"offset":9315},"indent":[]},"xvault":false,"sameFile":false,"to":{"fname":"volume-1.chapter-053"}}],"anchors":{},"children":[],"parent":"YmDf44XQK0snHWr4HCNuj","data":{}}
